checklist/__init__.py
checklist/checklist.py
checklist/task.py
pychecklist-0.1.0.data/scripts/checklist
pychecklist-0.1.0.dist-info/METADATA
pychecklist-0.1.0.dist-info/RECORD
pychecklist-0.1.0.dist-info/WHEEL
pychecklist-0.1.0.dist-info/top_level.txt
