Metadata-Version: 2.1
Name: pychecklist
Version: 0.1.0
Summary: A simple program for keeping track of tasks.
Home-page: https://github.com/dstathis/checklist/
Author: Dylan Stephano-Shachter
Author-email: dstephanoshachter@gmail.com
License: GPLv3
Platform: UNKNOWN
Classifier: Development Status :: 2 - Pre-Alpha
Classifier: Topic :: Utilities
Classifier: License :: OSI Approved :: GNU General Public License v3 (GPLv3)
Requires-Python: >=3
Requires-Dist: pptree
